{"cameraMode":{"drawMode":0,"name":"Shaded","section":"Shading Mode"},"sceneLighting":true,"audioPlay":false,"sceneViewState":{"showFog":true,"showMaterialUpdate":false,"showSkybox":true,"showFlares":true,"showImageEffects":true,"showParticleSystems":true,"showVisualEffectGraphs":true,"m_FxEnabled":true},"in2DMode":false,"pivot":{"x":355.5,"y":200.0,"z":0.0},"rotation":{"x":-0.06480064988136292,"y":0.9154860377311707,"z":-0.1640472561120987,"w":-0.36162808537483218},"size":407.8973388671875,"orthographic":false}